LICENSE
MANIFEST.in
README.md
setup.py
doc/conf.py
doc/config.rst
doc/index.rst
doc/modules.rst
doc/pymlab.rst
doc/pymlab.sensors.rst
src/quick_test.py
src/pymlab/__init__.py
src/pymlab/__main__.py
src/pymlab/config.py
src/pymlab/iic_server.py
src/pymlab/utils.py
src/pymlab.egg-info/PKG-INFO
src/pymlab.egg-info/SOURCES.txt
src/pymlab.egg-info/dependency_links.txt
src/pymlab.egg-info/requires.txt
src/pymlab.egg-info/top_level.txt
src/pymlab/sensors/__init__.py
src/pymlab/sensors/acount.py
src/pymlab/sensors/adc.py
src/pymlab/sensors/altimet.py
src/pymlab/sensors/atmega.py
src/pymlab/sensors/bus_translators.py
src/pymlab/sensors/clkgen.py
src/pymlab/sensors/gpio.py
src/pymlab/sensors/i2chub.py
src/pymlab/sensors/i2cio.py
src/pymlab/sensors/i2clcd.py
src/pymlab/sensors/i2cpwm.py
src/pymlab/sensors/iic.py
src/pymlab/sensors/imu.py
src/pymlab/sensors/light.py
src/pymlab/sensors/lightning.py
src/pymlab/sensors/lioncell.py
src/pymlab/sensors/lts.py
src/pymlab/sensors/mag.py
src/pymlab/sensors/motor.py
src/pymlab/sensors/rps.py
src/pymlab/sensors/rtc.py
src/pymlab/sensors/sdp3x.py
src/pymlab/sensors/sht.py
src/pymlab/sensors/thermopile.py
src/pymlab/sensors/windgauge.py
src/pymlab/tests/__init__.py
src/pymlab/tests/remote.py
src/pymlab/tests/sensors/__init__.py
src/pymlab/tests/sensors/config.py