Metadata-Version: 2.1
Name: pymlab
Version: 0.4
Summary: Toolbox for interfacing I2C sensors.
Home-page: https://github.com/MLAB-project/pymlab
Author: Jan Milík
Author-email: milikjan@fit.cvut.cz
License: Lesser General Public License v3
Download-URL: https://github.com/MLAB-project/pymlab/archive/refs/heads/master.zip
Keywords: TWI,IIC,I2C,USB,sensors,drivers
Platform: UNKNOWN
Classifier: Development Status :: 3 - Alpha
Classifier: Intended Audience :: Science/Research
Classifier: License :: OSI Approved :: GNU Library or Lesser General Public License (LGPL)
Classifier: Natural Language :: Czech
Classifier: Programming Language :: Python :: 2.6
Classifier: Programming Language :: Python :: 2.7
Provides: pymlab
License-File: LICENSE
